tacrpy/__init__.py
tacrpy/data_operations.py
tacrpy/analytics/__init__.py
tacrpy/data_fetcher/__init__.py
tacrpy/data_fetcher/googlesheets.py
tacrpy/data_fetcher/isvavai.py
tacrpy/data_fetcher/ssot.py
tacrpy/datahub/__init__.py
tacrpy/datahub/data_lineage.py
tacrpy/datahub/datasets.py
tacrpy/datahub/glossary.py
tacrpy/datahub/import_checks.py
tacrpy/datahub/openapi.py
pojdte_pane_budeme_si_hrat-1.0.3.dist-info/METADATA
pojdte_pane_budeme_si_hrat-1.0.3.dist-info/WHEEL
pojdte_pane_budeme_si_hrat-1.0.3.dist-info/top_level.txt
pojdte_pane_budeme_si_hrat-1.0.3.dist-info/RECORD
