Metadata-Version: 2.4
Name: pojdte_pane_budeme_si_hrat
Version: 1.0.3
Summary: Pojďte pane, budeme si hrát (tacrpy)
Author: velci panove tacru
Author-email: rozalie.bilkova@tacr.cz
Project-URL: Documentation, https://youtu.be/1RulQYSl1aw?feature=shared
Requires-Dist: pandas
Requires-Dist: gspread
Requires-Dist: numpy
Requires-Dist: requests
Requires-Dist: unidecode
Dynamic: author
Dynamic: author-email
Dynamic: description
Dynamic: project-url
Dynamic: requires-dist
Dynamic: summary
